LICENSE
README.md
pyproject.toml
setup.py
ptls/__init__.py
ptls/custom_layers.py
ptls/loss.py
ptls/make_datasets.py
ptls/make_datasets_spark.py
ptls/models.py
ptls/pl_fit_target.py
ptls/pl_inference.py
ptls/pl_inference_multimodal.py
ptls/pl_inference_spark.py
ptls/pl_train_module.py
ptls/size_reduction.py
ptls/swa.py
ptls/tb_interface.py
ptls/util.py
ptls/data_load/__init__.py
ptls/data_load/fast_tensor_data_loader.py
ptls/data_load/feature_dict.py
ptls/data_load/filter_dataset.py
ptls/data_load/iterable_processing_dataset.py
ptls/data_load/list_splitter.py
ptls/data_load/padded_batch.py
ptls/data_load/partitioned_dataset.py
ptls/data_load/utils.py
ptls/data_load/augmentations/__init__.py
ptls/data_load/augmentations/all_time_shuffle.py
ptls/data_load/augmentations/build_augmentations.py
ptls/data_load/augmentations/drop_day.py
ptls/data_load/augmentations/dropout_trx.py
ptls/data_load/augmentations/random_slice.py
ptls/data_load/augmentations/seq_len_limit.py
ptls/data_load/augmentations/sequence_pair_augmentation.py
ptls/data_load/data_module/__init__.py
ptls/data_load/data_module/cls_data_module.py
ptls/data_load/data_module/coles_data_module.py
ptls/data_load/data_module/cpc_data_module.py
ptls/data_load/data_module/cpc_v2_data_module.py
ptls/data_load/data_module/emb_data_module.py
ptls/data_load/data_module/emb_valid_data_module.py
ptls/data_load/data_module/map_augmentation_dataset.py
ptls/data_load/data_module/nsp_data_module.py
ptls/data_load/data_module/rtd_data_module.py
ptls/data_load/data_module/seq_to_target_data_module.py
ptls/data_load/data_module/sop_data_module.py
ptls/data_load/datasets/__init__.py
ptls/data_load/datasets/augmentation_dataset.py
ptls/data_load/datasets/dataloaders.py
ptls/data_load/datasets/duckdb_dataset.py
ptls/data_load/datasets/memory_dataset.py
ptls/data_load/datasets/parquet_dataset.py
ptls/data_load/datasets/parquet_file_scan.py
ptls/data_load/datasets/persist_dataset.py
ptls/data_load/iterable_processing/__init__.py
pytorch_lifestream.egg-info/PKG-INFO
pytorch_lifestream.egg-info/SOURCES.txt
pytorch_lifestream.egg-info/dependency_links.txt
pytorch_lifestream.egg-info/requires.txt
pytorch_lifestream.egg-info/top_level.txt