Metadata-Version: 2.1
Name: pytorch-lifestream
Version: 0.6.0
Summary: Lifestream data analysis with PyTorch
Author: 
Author-email: 
Classifier: Programming Language :: Python :: 3
Classifier: License :: OSI Approved :: MIT License
Classifier: Operating System :: OS Independent
Requires-Python: >=3.7
License-File: LICENSE
